aind_data_schema/__init__.py
aind_data_schema/base.py
aind_data_schema/components/__init__.py
aind_data_schema/components/configs.py
aind_data_schema/components/connections.py
aind_data_schema/components/coordinates.py
aind_data_schema/components/devices.py
aind_data_schema/components/identifiers.py
aind_data_schema/components/injection_procedures.py
aind_data_schema/components/measurements.py
aind_data_schema/components/reagent.py
aind_data_schema/components/specimen_procedures.py
aind_data_schema/components/stimulus.py
aind_data_schema/components/subject_procedures.py
aind_data_schema/components/subjects.py
aind_data_schema/components/surgery_procedures.py
aind_data_schema/components/wrappers.py
aind_data_schema/core/__init__.py
aind_data_schema/core/acquisition.py
aind_data_schema/core/data_description.py
aind_data_schema/core/instrument.py
aind_data_schema/core/metadata.py
aind_data_schema/core/model.py
aind_data_schema/core/procedures.py
aind_data_schema/core/processing.py
aind_data_schema/core/quality_control.py
aind_data_schema/core/subject.py
aind_data_schema/utils/__init__.py
aind_data_schema/utils/compatibility_check.py
aind_data_schema/utils/examples_generator.py
aind_data_schema/utils/exceptions.py
aind_data_schema/utils/json_writer.py
aind_data_schema/utils/merge.py
aind_data_schema/utils/schema_version_bump.py
aind_data_schema/utils/validators.py
aind_data_schema/utils/docs/doc_generator.py
aind_data_schema/utils/docs/model_generator.py
aind_data_schema/utils/docs/registries_generator.py
aind_data_schema/utils/docs/utils.py
aind_data_schema-2.4.0.dist-info/licenses/LICENSE
aind_data_schema-2.4.0.dist-info/METADATA
aind_data_schema-2.4.0.dist-info/WHEEL
aind_data_schema-2.4.0.dist-info/top_level.txt
aind_data_schema-2.4.0.dist-info/RECORD
