Metadata-Version: 2.4
Name: aind-data-schema
Version: 2.4.0
Summary: A library that defines AIND data schema and validates JSON files.
License: MIT
Classifier: Programming Language :: Python :: 3
Requires-Python: >=3.10
License-File: LICENSE
Requires-Dist: aind-data-schema-models<6,>=5
Requires-Dist: pydantic<2.12,>=2.7
Provides-Extra: dev
Requires-Dist: aind_data_schema[linters]; extra == "dev"
Requires-Dist: pydantic!=2.9.0,!=2.9.1,>=2.7; extra == "dev"
Requires-Dist: scipy; extra == "dev"
Requires-Dist: dictdiffer; extra == "dev"
Requires-Dist: semver; extra == "dev"
Provides-Extra: linters
Requires-Dist: codespell; extra == "linters"
Requires-Dist: black; extra == "linters"
Requires-Dist: coverage; extra == "linters"
Requires-Dist: flake8; extra == "linters"
Requires-Dist: interrogate; extra == "linters"
Requires-Dist: isort; extra == "linters"
Requires-Dist: aind-flake8-extensions<0.7,>=0.6; extra == "linters"
Provides-Extra: docs
Requires-Dist: sphinx; extra == "docs"
Requires-Dist: sphinx-jinja; extra == "docs"
Requires-Dist: furo; extra == "docs"
Requires-Dist: autodoc_pydantic; extra == "docs"
Requires-Dist: myst-parser; extra == "docs"
Requires-Dist: openpyxl; extra == "docs"
Provides-Extra: transforms
Requires-Dist: scipy; extra == "transforms"
Provides-Extra: viz
Requires-Dist: matplotlib; extra == "viz"
Dynamic: license-file
